{
  "document_id": "developer-guide.213",
  "document_type": "guide",
  "platform": "shopee",
  "content_ko": "# API 모범 사례 - 글로벌 상품 생성\n\n## 개요\n\n쇼핑몰 상품이 생성된 후, 해당 쇼핑몰 상품을 글로벌 상품에 매핑하여 중국어 또는 영어로 통합된 상품명 및 설명을 표시하고, 쇼핑몰 상품에 대한 업데이트를 동기화하도록 설정해야 합니다. Shopper는 자동으로 현지 언어로 번역합니다.\n\n- 쇼핑몰 상품에 대한 비동기 업데이트 실시간 업데이트를 지원합니다. 일부 실시간 동기화된 상품 정보의 경우, 판매자는 비동기 백그라운드 작업 실행 상태를 확인하여 쇼핑몰 상품 정보를 확인할 수 있습니다.\n- 상품 정보 동기화 판매자는 동기화 규칙을 구성할 수 있습니다. 예를 들어, 상품 정보 업데이트의 우선 순위입니다. 예를 들어, 공식 계산 결과에 따라 가장 높은 우선 순위를 가진 글로벌 상품입니다.\n\n**참고:** 쇼핑몰 상품이 Global API와 통합되고 쇼핑몰 상품이 `Global Product API`와 같은 Merchant API와 통합되는 경우, 쇼핑몰 사용자는 글로벌 상품으로 상품 정보를 관리해야 합니다. 주문 API와 같은 다른 API의 경우 변경이 필요합니다.\n\n- CMS에 대한 자세한 내용은 `CMSC API`를 사용하세요.\n- IMSC에 대한 자세한 내용은 `여기`를 클릭하세요.\n\n### CMSC/IMSC 계정 시스템\n\n이 통합을 통해 CMSC 또는 IMSC에 판매자 계정이 생성되면, 크로스보더 판매자에게만 적용됩니다.\n\n---\n\n## 용어 설명\n\n- **메인 계정**: 가장 높은 권한을 가진 기본 계정으로, 계정 소유자는 일반적으로 법인이며, 판매자의 모든 하위 계정을 생성하고 추가할 수 있는 권한을 가집니다. 메인 계정의 로그인 형식은 ACC_main입니다.\n- **쇼핑몰**: 사용자가 쇼핑몰 계정을 통해 찾는 페이지입니다. 여러 마켓에 대한 쇼핑몰은 하위 Merchant를 사용합니다. 하나의 CMSC 메인 계정은 여러 쇼핑몰을 가질 수 있습니다.\n- **아이템**: 쇼핑몰을 CMSC/IMSC 계정으로 업그레이드하면, 인증을 위한 기본 계정을 얻게 되며, 메인 계정만 API 호출을 할 수 있습니다. (판매자가 자체 계정을 선택하면 메인 계정과 하위 계정 모두 API 호출을 지원하며, 여러 Merchant에 사용되며, 각 Merchant에는 SPS 쇼핑몰 Merchant를 포함한 여러 마켓이 있을 수 있으며, Merchant 아래에는 동일한 마켓의 여러 쇼핑몰이 있을 수 있습니다.)\n\n---\n\n## 글로벌 상품 및 쇼핑몰 상품\n\n다음에서는 상품과 쇼핑몰 상품 간의 관계를 설명합니다.\n\n```\nMerchant 1\n\nSHIPBU - MTPSH 11\n\n└── US\n└── MX\n└── BR\n\n└── MTPSH 2\n    └── MTPSH 3\n    └── MTPSH 4\n```\n\n| 약어 | CMSC/IMSC | 설명 |\n|--------------|-----------|-------------|\n| MTPSH | 글로벌 SKU | 판매자는 상품명, 상품 설명, 이미지 등 기본적인 상품 정보를 MTPSH로 관리합니다. 차별화를 위해 마켓에 게시한 후, 쇼핑몰 SKU가 생성되며, 판매자는 쇼핑몰 상품 변경에 대한 마켓별 정보를 관리할 수 있습니다. |\n| MPSKU | 쇼핑몰 SKU | 쇼핑몰의 실제 쇼핑몰 상품 |\n\n---\n\n## 상품 관리 프로세스의 변경 사항\n\n글로벌 상품 관리 프로세스를 도입한 후, 상품 관리 프로세스에 변경 사항이 있습니다.\n\n### 1. 상품 생성\n\n**온라인 상품 판매 장치 API**를 통해 새로운 상품 생성 프로세스를 진행한 다음, API를 사용하여 `product/createProduct`를 호출하여 더 많은 상품 카테고리의 쇼핑몰 상품과 쇼핑몰 상품을 게시하고 동기화합니다. 게시 프로세스에 대한 자세한 내용은 [링크]를 참조하세요.\n\n### 2. 필드 관리\n\n상품 관련 필드를 세 가지 범주로 나눕니다.\n\n1. **MTPSH에서만 관리할 수 있는 필드**: 이러한 필드는 카테고리, 속성 등과 같은 차이점을 만들 수 없습니다. MTPSH에서 관리할 수 있는 필드는 둘 다 업데이트할 수 있습니다. 모든 글로벌 필드는 모든 쇼핑몰 상품으로 업데이트할 수 있지만, MTPSH가 판매자의 공개 관리 필드인 경우입니다. 이러한 필드는 상품명 및 상품 설명과 같이 (선택)적으로 차별화할 수 있습니다. 필드에서 MTPSH를 통해 필드를 선택해야 하는 경우, 계정은 자동으로 쇼핑몰 상품으로 이전됩니다. 선택하지 않으면 계정은 동기화 규칙을 구성하고 우선 순위는 글로벌 상품에 따라 업데이트됩니다.\n\n2. **MPSKU에서만 관리할 수 있는 필드**: 이러한 필드는 물류 정보와 같이 글로벌 상품을 통해서만 관리할 수 있습니다.\n\n| API 필드 | MTPSH에서 관리 | MPSKU에서 관리 |\n|-----------|----------------|-----------------|\n| category_id | ✓ | ✗ |\n| attribute | ✓ | ✗ |\n| brand | ✓ | ✓ |\n| item_name | ✓ | ✓ |\n| description | ✓ | ✓ |\n| weight | ✓ | ✗ |\n| dimension | ✓ | ✗ |\n| price | ✗ | ✓ |\n| stock | ✗ | ✓ |\n| image/video | ✓ | ✓ |\n| days_to_ship | ✓ | ✓ |\n| item_status | ✓ | ✓ |\n| condition | ✓ | ✓ |\n| item sku | ✗ | ✓ |\n| size_variation structure | ✓ | ✗ |\n| size_variation name/caption | ✓ | ✓ |\n| logistics | ✗ | ✓ |\n\n---\n\n### 다음 사항에 유의하십시오.\n\n- 쇼핑몰을 CMSC/IMSC로 업그레이드하면 MTPSH의 제한은 5k이고 MTPSH에서 매일 게시되는 MPSKU는 2en MPSKU입니다. MTPSH의 제한은 MTPSH가 1K인 경우입니다. 기본 게시 크기 MTPSH가 2en K인 경우 MTPSH의 재고는 2en 차이점을 사용할 수 있습니다.\n\n- 국가마다 재고가 다릅니다. 글로벌 게시물이 게시된 모든 쇼핑몰 상품은 다릅니다. 그러나 쇼핑몰 상품은 글로벌 상품에 영향을 주지 않고 개별적으로 삭제하고 통합할 수 있습니다.\n\n---\n\n## 3. 카테고리 호출\n\n### 상품 목록\n\n**글로벌 상품 생성:** Shopper 크로스보더 관리에 처음 연결하는 경우, **Product standard information API** 또는 **Global product sale API**를 통해 발행하는 것이 좋습니다. 자세한 내용은 [링크]를 참조하세요.\n\n#### 3.1 카테고리 호출\n\n`/api/v1/global_product/category`를 사용합니다.\n\n**다음 사항에 유의하십시오.**\n- 카테고리가 다른 경우 API는 동일한 카테고리 트리 데이터를 반환합니다.\n- 카테고리가 다른 경우 동일한 응답 구조를 반환하더라도 카테고리 속성 및 정보(카테고리 A)는 말레이시아 쇼핑몰에서는 사용할 수 없지만 브라질 쇼핑몰에서는 사용할 수 있는 경우, 카테고리를 게시하지 않도록 안내하지만 글로벌 상품은 업데이트할 수 있습니다. 카테고리 정보에 대한 자세한 내용은 로컬에서 사용할 수 있는 API 호출을 참조하십시오.\n\n#### 3.2 추천 카테고리 호출\n\n```\n/api/v1/global_product/get_recommend_category\n```\n\n---\n\n# 개발자 가이드 - 카테고리 및 상품 정보 가져오기\n\n## 3.1 카테고리 가져오기\n\nAPI: `tv.taobao.products.get_category`\n\n다음 사항에 유의하십시오.\n- 판매자는 동일한 카테고리를 너무 자주 선택할 수 없습니다.\n- `tv.taobao.products.get_category` API는 글로벌 상품에 사용할 수 있는 카테고리를 반환하지만, 인증된 API가 상품을 성공적으로 생성하기에 충분하지 않은 상황이 발생할 수 있습니다. 이 경우 Aliexpress PD에 최신 사용 가능한 카테고리를 확인해야 합니다. 또한 Seller Center를 통해 상품을 게시하여 각 마켓에 사용할 수 있는 카테고리를 알 수 있으며, `tv.product.get_category` API를 호출할 수 있습니다.\n\n## 3.2 속성 가져오기\n\nAPI: `tv.global_product.category_properlised`\n\n## 3.3 속성 값 가져오기\n\nAPI: `tv.global_product.get_attribute_traits`\n\n다음 사항에 유의하십시오.\n속성 이름, 필수, 요청/매개변수 및 필수, 지역 응답, 매개변수와 같은 일부 속성의 경우, 예를 들어 맛과 같은 일부 속성의 경우 대만 마켓의 상품만 필수이므로 판매자가 대만 마켓에 게시하지 않으려면 무시할 수 있으며 글로벌 상품 생성 프로세스를 확인할 필요가 없으므로 속성 목록에 표시됩니다. 이 경우 무시하십시오. 실제 상황은 해당 값이 필요한지 여부에 따라 다릅니다. 이러한 나머지 속성의 경우:\n- 목록 포인트의 특수 자동 기능을 제외하고 마켓 중 하나가 값을 요청하는 한 모든 속성이 반환되고 attribute_name을 채워야 하며 tv.product_product.get_attribute_traits API를 사용해야 합니다.\n\n## 3.4 추천 속성 가져오기\n\nAPI: `tv.global_product.get_ai_attribute_traits`\n\n## 3.5 사용 가능한 브랜드 목록 가져오기\n\nAPI: `tv.global_product.get_brand_list`\n\n## 3.6 배송 일수 가져오기\n\nAPI: `tv.global_product.get_day_to_ship`\n\n다음 사항에 유의하십시오.\n`tv.global_product.get_day_to_ship`은 모든 마켓에서 채울 수 있는 배송 일수를 연결하여 반환합니다.\n\n```json\n\"data_is_ship_range_list\": [\n  {\n    \"country\": \"SG\",\n    \"ship\": \"15\"\n  },\n  {\n    \"country\": \"MY\",\n    \"ship\": \"15\"\n  }\n]\n```\n\n일괄 처리 사례: 글로벌 상품에 대한 일괄 배송 일수는 7, 8, 10, 11, 12 및 13입니다.\n`tv.product.get_day_to_ship`의 풍부한 테이블을 저장하여 각 마켓에 대한 더 정확한 배송 일수를 얻을 수도 있습니다.\n\n## 3.7 카테고리에 대한 정보 가져오기\n\nAPI: `tv.global_product.get_ai_attribute_traits`\n\n다음 사항에 유의하십시오.\n자세한 내용은 `announcement`를 검토하는 최신 화이트리스트를 설정하고 있습니다.\n\n## 3.8 글로벌 상품 제한 가져오기\n\nAPI: `tv.global_product.category_rules_get`\n\n다음 사항에 유의하십시오.\n현재 `category_name_product_base` 모든 PGU 상품 제한/금지 이름 및 옵션 이름에 대해 금지된 정보가 포함되어 있으며 가져올 수 있습니다. 중국어와 영어 번역이 정확히 동일하지 않으므로 영어 번역, 마켓 언어와 같은 정보는 중국어와 영어가 다른 중국어 길이 제한을 갖도록 번역을 사용하고 다른 언어는 중국어 문자와 동기화됩니다. (중국어 문자 제한은 30이고 다른 언어는 중국어 문자 제한 60과 동기화됩니다.)\n\n```json\n\"cnt_length_restriction\": 2.44,\n\"cnt_length_rules\": \"length\" = 240,\n\"eng_length_rules\": 2.5 * \n    cnt_length,\n\"local_limit\": 500\n```\n\n다시 말해, 판매자가 상품명을 영어로 입력하면 최대 문자 수는 1이 500입니다. 판매자가 상품명을 중국어로 입력하면 최대 문자 수는 1이 250입니다(500/2 = 44 = 250.50 문자이기 때문입니다).\n\n---\n\n## 4. 글로벌 상품 생성\n\n글로벌 상품 구성은 글로벌 상품을 생성하기 전에 특정 요구 사항 또는 규칙을 충족해야 합니다.\n판매자는 글로벌 상품을 생성하기 전에 CNSC/MNSC에 로그인하여 온보딩 및 환율 구성을 완료해야 합니다. 그렇지 않으면 `unauthorized` 등과 같은 오류가 발생합니다.\n\n- 온보딩 절차는 https://shopee.ph/edu/article/1741을 참조하십시오.\n- 통화 설정: https://seller.shopee.ph/account/settings/address\n\n---\n\n## 4.2 메인 계정 인증 완료\n\n`Authorization/UserAuthorization`을 참조하십시오.\n\n## 4.3 메인 계정 아래의 Merchant ID 목록 및 쇼핑몰 ID 가져오기\n\n다음 API를 호출할 수 있습니다.\n- 인증 후 `tv.seller.get_authorized_shop` API를 통해 현재 인증된 Merchant ID 목록 및 쇼핑몰 ID 목록을 가져옵니다.\n- API를 호출하여 인증을 완료하기 전에 API를 호출하여 `tv.shop.get_shop_list` API를 호출하여 ID와 기본 쇼핑몰 및 계열 쇼핑몰 간의 관계를 포함하여 각 인증된 쇼핑몰의 정보를 가져옵니다.\n- 기본 쇼핑몰 정보를 가져오려면 `tv.shop.get_shop_info` API를 호출하여 `s1_main_shop` 필드가 반환되지 않았는지 확인합니다.\n- SIP 기본 쇼핑몰인 경우 `s1_gm1test.test.the_sip_info` 쇼핑몰 필드가 반환됩니다.\n- 메인 계정이 여러 `s1_gm1test.test.the_sip_info` 쇼핑몰 필드를 인증한 경우 반환되지 않습니다.\n\n---\n\n## 4.4 상품 번역 정보 동기화\n\n번역 지원:\n판매자는 CNSC/MNSC 또는 API를 통해 사전에 번역된 정보가 쇼핑몰 상품에 자동으로 동기화되도록 할 수 있습니다.\n\nCNSC/MNSC 스크린샷:\n\n**Merchant 설정**\n\n[설정 유형, 다양한 상태 필드 및 설명에 대한 열이 있는 Merchant 설정을 보여주는 테이블]\n\n**Merchant 설정** 섹션에는 다음 옵션이 표시됩니다.\n- Taobao 지역 상품 정보 동기화\n- 다음 설정을 표시합니다.\n  - 동기화 옵션\n  - 동기화됨 ✓\n  - 동기화되지 않음 ✓\n  - 카테고리(EN/CN 표시기 포함)\n  - 색상(빨강, 파랑, 흰색)\n  \n*sync_ authorized는 동기화되지 않음을 의미해야 합니다.*\n\n키 필드는 `tv.global_product.pre_trans_sync.txt`이며, *true*는 동기화를 의미하고 *false*는 동기화되지 않음을 의미합니다.\n\n---\n\n## 4.5 이미지 업로드\n\n## 4.5.1 미디어 파일 업로드\n\nShopee의 미디어 공간에 미리 저장된 파일을 생성하거나 편집하기 위해 API를 호출하기 전에 media_upload 관련 API를 호출하여 파일을 업로드해야 합니다. 자세한 내용은 \"미디어 파일 업로드\" 섹션의 `show`를 참조하십시오.\n\nCNSC/MNSC 미디어 공간에서 상품 이미지 또는 속성 이미지를 사용하려면 `tv.global_product.get_image_list` API를 호출하여 지정된 카테고리 아래의 메인 이미지 목록을 가져올 수 있습니다.\n\n---\n\n## 5) 카테고리별 업로드\n\n판매자가 `tv.global_product.get_category` API에서 `has_children=false`를 반환하는 카테고리만 선택할 수 있도록 카테고리별로 업로드하는 것을 지원합니다.\n\n---\n\n## 6) 번역 요구 사항\n\n해외 Aliexpress Merchant에게 최상의 서비스를 제공하기 위해 다양한 상품 유형(이미지, 텍스트, 상품 설명 등)에 대한 엄격한 규칙을 적용하여 비즈니스가 올바르게 운영되도록 할 것입니다. 판매자는 간체 중국어, 영어 및 숫자를 입력할 수 있습니다. 간체 중국어와 번체 중국어를 혼합하지 마십시오. 현지 언어로 번역되지 않는 현지 언어 단어를 충족하는 경우. 다음 요구 사항은 필수입니다.\n\n번역 정보:\n크로스보더 상품 설명은 간체 중국어, 영어 및 숫자만 입력할 수 있습니다.\n\n제한 정보:\n금지된 콘텐츠: 외설 및 민감한 단어에 대해서는 간체 중국어, 영어 및 숫자만 입력할 수 있습니다.\n\n---\n\n## 4.6 글로벌 상품 정보 업로드\n\n글로벌 상품 정보를 업로드할 때 다음 사항에 유의하십시오.\n현재 미완료된 판매자가 설명을 위해 쇼핑몰을 선택하는 것을 지원합니다. 설명 부분에 이미지를 추가하거나 업로드하는 방법에 대한 자세한 내용은 `FAQ`를 참조하십시오.\n\n이미지 업로드 정보:\n크로스보더 Seller Center 판매자는 이제 가격 책정을 위해 모든 UPC를 만들 수 있습니다. 크로스보더 판매자는 가격 책정에 USD를 사용할 수 있으며, 상품 가격 없이 `tv.global_product.product_add` API 항목의 가격을 수정할 수 있습니다.\n\n가격 정보:\n단일 유형 상품의 경우 가격은 환율로 직접 변환되지 않습니다.\n\n---\n\n## 4.6.1 글로벌 상품 재고 업로드\n\nAPI: `tv.global_product.product_add`\n\n---\n\n# 4.4.3 글로벌 상품 설명 업로드\n\n**훌륭한 상품 설명은 간체 중국어, 영어 및 숫자로 구매자를 유치합니다.**\n\n## 중요 참고 사항\n현재 이미지를 설명에 삽입하기 위해 임베디드 비디오를 지원합니다. 비디오를 삽입하는 방법에 대한 자세한 내용은 [FAQ](#)를 참조하십시오.\n\n---\n\n## 4.4.3 글로벌 상품 가격 업로드\n\n해외 크로스보더 판매자는 가격 책정에 RMB 또는 USD를 사용할 수 있습니다. 해외 크로스보더 판매자는 가격 책정에 USD를 사용할 수 있으며, 국내 크로스보더 판매자는 가격 책정에 RMB를 사용할 수 있습니다. [YJ 변환율 규칙/일반 비율](#) API의 경우 판매자가 선택한 통화에 따라 해당 통화의 다른 가격 단위가 있습니다.\n\n---\n\n## 4.4.1 글로벌 상품 재고 업로드\n\n업로드된 재고는 위험 통제 검토를 거칩니다. 검토에 통과하지 못하면 업로드된 재고의 일정 비율이 동결됩니다.\n\n예: MT3501이 3개의 MPU(s)를 게시하는 경우 MPU(s8, MPU(s8, MPU(s8)이면 MT3501 재고가 100으로 설정되면 재고 MPU(s1+MPU(s2+MPU(s3)=120이면 [MPU(s1, MPU(s2 및 MPU(s3은 해당\n| tier_index[2] | M | 300 | 10 | - |\n\n---\n\n## API 요청 예시:\n\n**Endpoint:** `sz.global_product_tier_tier_variation API request example:`\n\n```json\n{\n  \"global_item_id\": 1000170002,\n  \n  \"tier_variation\": [\n    {\n      \"name\": \"size\",\n      \n      \"option_list\": [\n        {\n          \"option\": \"S\",\n          \n          \"image\": {\n            \"image_id\": \"030ce4fd59c82e09a6bc78c8c3e7f\"\n          }\n        },\n        {\n          \"option\": \"L\",\n          \n          \"image\": {\n            \"image_id\": \"19bce4fd59c82e09a6bcf78c8c7f\"\n          }\n        },\n        {\n          \"option\": \"M\"\n        }\n      ]\n    }\n  ],\n  \n  \"model_list\": [\n    {\n      \"tier_index\": [0],\n      \n      \"original_price\": 100,\n      \n      \"global_model_sku\": \"sku1\",\n      \n      \"model_stock\": 10\n    },\n    {\n      \"tier_index\": [1],\n      \n      \"original_price\": 200,\n      \n      \"global_model_sku\": \"sku2\",\n      \n      \"model_stock\": 20\n    },\n    {\n      \"tier_index\": [2],\n      \n      \"original_price\": 300,\n      \n      \"global_model_sku\": \"\",\n      \n      \"model_stock\": 30\n    }\n  ]\n}\n```\n\n---\n\n## 4.8.2 2단계 베리에이션 생성\n\n상품에 색상 및 사이즈 사양이 있다고 가정합니다. 색상은 빨간색과 파란색을 포함하고, 사이즈는 xl, s, l 쿠키를 포함합니다.\n\n### 예시 테이블:\n\n| tier_index | color | size | price | stock | sku |\n|------------|-------|------|-------|-------|-----|\n| tier_index[0][0] | Red | S | 100 | 10 | sku1 |\n| tier_index[0][1] | Red | L | 200 | 20 | sku2 |\n| tier_index[1][0] | Blue | XL | 500 | 30 | sku3 |\n| tier_index[1][1] | Blue | L | 400 | 40 | sku4 |\n\n---\n\n## API 요청 예시:\n\n**Endpoint:** `sz.global_product_tier_tier_variation API request example:`\n\n```json\n{\n  \"global_item_id\": 1000170002,\n  \n  \"tier_variation\": [\n    {\n      \"name\": \"Color\",\n      \n      \"option_list\": [\n        {\n          \"option\": \"Red\"\n        },\n        {\n          \"option\": \"Blue\",\n          \n          \"image\": {\n            \"image_id\": \"030ce4fd59c82e09a6bc78c8c3e7f\"\n          }\n        }\n      ]\n    },\n    {\n      \"name\": \"Size\",\n      \n      \"option_list\": [\n        {\n          \"option\": \"S\"\n        },\n        {\n          \"option\": \"XL\"\n        }\n      ]\n    }\n  ]\n}\n```\n\n---\n\n# 개발자 가이드 - 상품 베리에이션 구성\n\n## JSON 구조\n\n```json\n]\n},\n{\n  \"name\": \"size\",\n  \n  \"option_list\": [\n    {\n      \"option\": \"XL\"\n    },\n    {\n      \"option\": \"L\"\n    }\n  ]\n}\n],\n\n\"model\": [\n  {\n    \"tier_index\": [0,0],\n    \n    \"original_price\": 100,\n    \n    \"normal_stock\": 10,\n    \n    \"global_model_sku\": \"sku1\"\n  },\n  {\n    \"tier_index\": [0,1],\n    \n    \"original_price\": 200,\n    \n    \"normal_stock\": 20,\n    \n    \"global_model_sku\": \"sku2\"\n  },\n  {\n    \"tier_index\": [1,0],\n    \n    \"original_price\": 300,\n    \n    \"normal_stock\": 30,\n    \n    \"global_model_sku\": \"sku3\"\n  },\n  {\n    \"tier_index\": [1,1],\n    \n    \"original_price\": 400,\n    \n    \"normal_stock\": 40,\n    \n    \"global_model_sku\": \"sku4\"\n  } ]\n}\n```\n\n## 중요 사항\n\n**다음 사항에 유의하십시오:**\n\n- **정의한 옵션은 Shopee 몰 측에 순서대로 표시됩니다. Shopee는 현재 최대 2단계 베리에이션 정의만 지원합니다.**\n\n- **각 베리에이션에 대한 이미지를 정의할 수 있습니다. 2단계 베리에이션 상품인 경우 첫 번째 레이어의 옵션만 정의할 수 있습니다. 즉, 예시에서 색상을 기준으로 베리에이션 이미지를 정의할 수 있지만 크기를 기준으로 정의할 수는 없습니다. 베리에이션 이미지를 추가하려면 첫 번째 레이어의 모든 옵션이 이미지를 정의해야 합니다. 이미지는 V2 미디어 업로드 이미지 API를 호출하여 업로드해야 합니다.**\n\n- **tier_index는 0부터 시작해야 하며 오버플로되지 않아야 합니다. 그렇지 않으면 오류가 보고됩니다.**\n\n- **아이템 데이터 생성에 지연이 있을 수 있으므로 아이템 생성 후 5초 간격으로 베리에이션을 생성하는 것이 좋습니다.**\n\n## 다음 단계\n\n다음으로 **글로벌 상품 게시 방법**을 검토하십시오.",
  "translated_at": "2025-10-16T08:42:17",
  "char_count": 12389,
  "metadata_ko": {
    "title": "API 모범 사례 - 글로벌 상품 생성",
    "summary": "본 가이드는 통합된 글로벌 상품 카탈로그와 상점 상품을 동기화하는 데 중점을 두고 글로벌 상품을 생성하고 관리하기 위한 모범 사례를 설명합니다. 용어, 상품 관리 변경 사항, 카테고리 및 상품 정보에 대한 API 사용법을 다룹니다.",
    "keywords": [
      "Global Product",
      "Shop Product",
      "CMSC",
      "IMSC",
      "MTPSH",
      "MPSKU",
      "Product Synchronization",
      "API",
      "Product Categories",
      "Product Attributes"
    ],
    "category": "모범 사례",
    "tags": [
      "상품 관리",
      "API Integration",
      "Global Commerce",
      "국경 간 거래",
      "Synchronization"
    ],
    "difficulty": "medium",
    "importance": 4,
    "use_cases": [
      "새로운 글로벌 상품 카탈로그 생성",
      "여러 상점 및 시장에서 상품 정보 동기화",
      "글로벌 상품 속성 및 카테고리 관리",
      "CMSC/IMSC 계정 시스템과 통합",
      "실시간 상품 정보 업데이트"
    ],
    "related_apis": [
      "Global Product API",
      "Product standard information API",
      "Global product sale API",
      "/api/v1/global_product/category",
      "/api/v1/global_product/get_recommend_category",
      "tv.taobao.products.get_category",
      "tv.global_product.category_properlised",
      "tv.global_product.get_attribute_traits",
      "tv.global_product.get_ai_attribute_traits",
      "tv.global_product.get_brand_list",
      "tv.global_product.get_day_to_ship"
    ]
  },
  "metadata_translated_at": "2025-10-16T08:42:19"
}