{
  "document_id": "developer-guide.697",
  "document_type": "guide",
  "platform": "shopee",
  "extracted_at": "2025-10-16T09:27:52",
  "extracted_text": "# Quotation API (Entrance Ex.)\n\n## API Rest Practice > Brand Upon API Best Prac... > Quotation API (Entrance Ex.\n\n### Shipping Quote API\nThis API is available to specify where prices products are out supported by Shoppe's own logistics API (a shipments and weight, in accordance with the rules determined by Shoppe's sales team.\n\n---\n\n## Shipping Quote URL\n\nThis tool allows sellers to send Shoppe-estimated shipping costs and delivery times, which will be displayed to buyers at the time of purchase. It can be further added sold and sold per the unrelated payment requirements.\n\n**Note:** The seller tool has opted to integrate directly with Shoppe to connected their quote URL or connect via an integration API.\n\n---\n\n## Requirements for approval/integration\n\nSeek and complete from the Quotation API to use Shoppe-supported low Cost Integration from Entrance Express (where) requires review and approval from the Shoppe team before it can go live. To be approved by the Shoppe team, you must:\n\n- Freight-Guard API (Lazada Partnership)\n- Opt into the Sellers Warranty Program and follow the Product Quality guidelines\n- The URL has be specific, structure, providing flexibility in configuration\n- Quote and order API calls; receipt and respond can transform less than 3sec(s.)\n- Quote and partner_id calls API; receipt and response transform less than 1 sec(s.)\n- Continuously keep registered directly through the Seller Center\n- Ensure tracking for quote revised and completed call the backend for processing tracking in a later stage\n- Must meet Shoppe's Late Ship Rate (LSR)/Late Delivery Rate (LDR)/ Invalid Tracking Rate (ITR)/ Return requirements\n   Note: The above requirements must be met by the seller's \"best support\" or their EXPRESS/Integration, it's recommended to review to review from Shoppe Supported Low Cost Integration (where) system to be supported carrier.\n- It is strongly encouraged to integrate with the Shipment API, Order (Arrange Pickup API) and Tracking API\n   Note: If the Entrance Express API is only used for quotation URL's. To use any API, it is necessary to create a token first.\n- Since the API allows for quoting the Buyer's desire to track inventory (all the native phone).\n\nIn an able to perform the integration and track where: it is site (necessary)\n- Submit all inputs to quote revised and tracked; and it; Shoppe-review (evidence letters to the API)\n- To have all (PUT that is capable of rating Logistics) to quote letters your and distribute letters to the API?)\n\nOnce all these rates are completely sent to Shoppe (through the API or a tool) or at least if their cutters, which will be reflected as further order sent to the processing, buyers will be able to see it during checkout.\n\n---\n\n## Quotation API Request and Response Flow\n\nShoppe will be calling Quotation API in 2 scenarios, which have different request and response parameters (some overlap) as listed in Request + Response > [Default]\n\n[Diagram showing API Request and Response Flow]\n\n---\n\n## Quotation API Request and Response (Default)\n\n### Request parameters (query):\n\n| Name | Example | HTTP Address |\n|------|---------|--------------|\n| URL | https://api.folder | URL provided by TSP or seller |\n\n| Name | Type | Example | Description |\n|------|------|---------|-------------|\n| partner_id | int | 1 | The partner ID assigned after successful registration (Required for all requests) |\n| timestamp | timestamp | 1670000000 | Timestamp from Shoppe in second format (or all requests). Expires in 5 minutes |\n| sign | string | e19d0e52237f91fab0f0a84e7c0311f6f1b4374bf0540a56e04d50689f51060d | Signature generated by the seller. IP=\"quotation_id: api_key call; timestamp and partner_key: api key (or HMAC+SHA256 hashing algorithm) provided at https://open.shopee.com/documents/v2/v2.logistics.get_tracking?module=94&type=1 for detail steps. |\n\n### Base Request Parameters\n\n| Request Parameters | | | | |\n|--------------------|------|------|---------|-------------|\n| Name | Type | Mandatory | Example | Description |\n| channel_id | int | TRUE | M006 | Unique identifier for the logistic channel in Shoppe |\n| entry_id | int | TRUE | 15224678 | Unique identifier for each order |\n| origin_zip_code | string | TRUE | 12345000 | Seller's zip code with 8 digits, only numbers without periods and dashes |\n| destination_zip_code | string | TRUE | 12345000 | Buyer's zip code with 8 digits, only numbers without periods and dashes |\n| destination_lat_long | object | TRUE | | Latitude of buyer's delivery location Value should be within -90.00 < x < 90.00. This value is provided for 3PL to verify the exact location address they may use |\n| longitude | float | TRUE | -23.5745841 | Longitude of buyer's delivery location Value should be within -180.00 < x < 180.00. This value is provided for 3PL to verify the exact location address they may use |\n| items | array | TRUE | | Product list |\n| item_id | int | TRUE | 15224678 | Item Identification on Shoppe |\n| title | string | FALSE | Item_title | SKU / registered by the seller (if) additional information |\n| model_id | int | FALSE | 15224678 | Identification of the model registered on Shoppe Note: In PVP supply, the model_id is Always '0', As well as price, qty, length, width, height, weight (numerals) |\n| model_title | string | FALSE | model_sku | Model SKU registered by the seller (if) on Shoppe |\n| category_id | int | TRUE | 15224678 | Category registered on Shoppe Note: In PVP supply, the model_id of is Always '0', As well as price, qty, length, width, height, weight (numerals) |\n| quantity | int | TRUE | 15224678 | Product's quant items |\n| price | float | FALSE | 150.4 | Product's price |\n| dimensions | object | TRUE | | Product dimensions |\n| length | int | TRUE | 10 | Length in centimeters for 1 quantity |\n| width | int | TRUE | 10 | Width in centimeters for 1 quantity |\n| height | int | TRUE | 10 | Height in centimeters for 1 quantity |\n| weight | int | TRUE | 100 | Weight in grams for 1 quantity |\n\n### Response Parameters / Quote Response (SP's)\n\n| Name | Type | Mandatory | Example | Description |\n|------|------|-----------|---------|-------------|\n| status | string | True | | Identifier of the quote made by the seller |\n| message | string | True | | Buyer's zip code |\n| request_id | string | True | | API call identifier |\n\n### Response Parameters / Quote Response (success)\n\n| Response Parameters | | | | |\n|---------------------|------|----------|---------|-------------|\n| Name | Type | Mandatory | Example | Description |\n\n---\n\n# API Documentation\n\n## Response Parameters / Quote Response (success)\n\n### Response Parameters\n\n| Name | Type | Mandatory | Example | Description |\n|------|------|-----------|---------|-------------|\n| channel_id | int | TRUE | 90028 | Unique identifier for the logistic channel |\n| quotation_id | int | TRUE | 091234000 | Identifier of the quote made by the system |\n| destination_zip_code | string | TRUE | 09123400 | Buyer's zip code |\n| destination_url_lang | double | FALSE | - | \"Location x Longitude\" or \"buyers location\" should be enter \"-180 < x < 180\" |\n| sellists | float | FALSE | -46.7354220599999 | Latitude of buyer's delivery location. Value should be enter \"-90 < x < 90\" |\n| longitude | float | FALSE | -23.5745491 | Longitude of buyer's delivery location. Value should be enter \"-180 < x < 180\" |\n| packages | array | TRUE | - | Package List |\n| dimensions | object | TRUE | - | Product dimensions |\n| width | int | TRUE | 10 | Width in centimeters |\n| length | int | TRUE | 10 | - |\n| height | int | TRUE | 10 | Height in centimeters |\n| weight | int | TRUE | 100 | Weight in grams |\n| sku | string | TRUE | - | Product sku |\n| seller_id | int | FALSE | 12345678 | Identification on Shopee |\n| sku | string | FALSE | sku_item | SKU registered by the seller on Shopee |\n| model_id | int | FALSE | 12345678 | Identification of the model registered on Shopee |\n| model_sku | string | FALSE | model_sku | Model SKU registered by the logistic channel on Shopee |\n| category_id | int | FALSE | 12345678 | Item category registered on Shopee |\n| quantity | int | TRUE | 2 | Quantity of items |\n| price | int | TRUE | 130.4 | Product price |\n| dimensions | object | TRUE | - | Product dimensions |\n| width | int | TRUE | 10 | Width in centimeters |\n| length | int | TRUE | 10 | - |\n| height | int | TRUE | 10 | Height in centimeters |\n| weight | int | TRUE | 100 | Weight in grams |\n| quotations | array | TRUE | - | List of shipping quotes |\n| price | int | TRUE | 130.4 | Shipping cost displayed to Users |\n| handling_time | int | TRUE | 20 | Order preparation time in minutes. If it exceeds 24 hours (1440 minutes), this value includes the date 3. The date includes the handling_time calculated in hours 3 (not minutes) |\n| shipping_time | int | TRUE | 10 | Order transit time in days in minutes |\n| promise_time | int | TRUE | 30 | Sum of handling time + shipping time in minutes |\n| service_code | string | TRUE | M1020 | Code that identifies the carrier in the context of the other model. Example: Correios API (SEDEX - AR, PAC - M1010); External Integrations API (ex: \"Correio Expresso - M1007\") |\n| letback_promise_time | int | TRUE | 30 | Average order preparation and dispatch time in minutes. Value to be shown to the buyer when there is an SLA operation API error |\n\n**Default response for errors not mapped in the error table**\n\n```json\n*code#* : \"internal system error\",\n*message* : \"internal system error\"\n```\n\n**Expected error codes:**\n\n### HTTP status code\n\n| HTTP status code | Error | Message | Action/Description |\n|-----------------|-------|---------|-------------------|\n| 400 | success/API_call_error | success/API_call_error Empty | False |\n| 403 | error_forbidden_id | there is no partner_id (it didn't publish_id) | False |\n| 403 | error_partner_id | partner_id is invalid | False |\n| 404 | error_sign | your sign is invalid | False |\n| 404 | error_sign | there is no sign in query | False |\n| 422 | error_timestamp | your timestamp is invalid | False |\n| 423 | error_shop_id | there is no shop_id (in body) | False |\n| 424 | error_shop_id | The shop_id is invalid | False |\n| 424 | invalid_arg_url_code | The origin_zip_code is invalid | False |\n| 424 | invalid_destination_PA_code | The destination_zip_code is invalid | False |\n| 424 | error_quotation_result | The quotation shipment is unavailable. | False |\n| 400 | Invalid item_id | The item_id is invalid | False |\n| 400 | Invalid model_id | The model_id is invalid | False |\n| 400 | Invalid sku | The sku is NOT valid | False |\n| 400 | Invalid category_id | The category_id is invalid | False |\n| 400 | Invalid quantity | The quantity is invalid | False |\n| 400 | Invalid price | The price is invalid | False |\n\n---\n\n# Quotation API Request and Response (Fastback)\n\n## Request Parameters (Body)\n\n| Name | Type | Mandatory | Example | Description |\n|------|------|-----------|---------|-------------|\n| msg_id | int | TRUE | 112345678 | Unique identifier for each order |\n\n## Response Parameters (Body)\n\n| Name | Type | Mandatory | Example | Description |\n|------|------|-----------|---------|-------------|\n| msg_id | int | TRUE | 112345678 | Unique identifier for each order |\n| fastback_promise_time | int | TRUE | 30 | Average order preparation and shipping time in minutes. Difference value will be used if the order contains different logistics settings or when there are item fails. |\n\n## Response validation (with Shopee URL)\n\n- Once uploaded, a validation link will be sent to seller. It is a link that should be used to validate and report any necessary corrections.\n- URL: \"https://seller.shopee.ph/gou-chat-api-link?to-secondarycomplication_quotation_anwsers\"\n- For further assist with the URL and fully implemented with Shopee, seller is an example process showing how to use the response format calculation URL.\n\n## Response Time Limit (of the quotation)\n\n- Considering that checkout is the most crucial moment in the user experience during the purchase, it is essential to ensure the best possible experience for the buyer.\n- Therefore, the estimated time limit of this process is between 8 to 10 seconds\n- Response times longer than 2000s will not be permitted, making integration impossible. Therefore, optimizing this parameter is crucial achieving the best possible user experience.\n\n---\n\n# Contingency Table\n\nThe Contingency Freight is the default freight calculation. In case there is a problem with freight quotation out API (Status at least 500 for requests)\n\n## Shipping Value Settings for Contingency\n\nFor the contingency to work, the seller must register the shipping values and enable the Foreign Express channel.\nAccess the menu to configure your Shipping Values.\n\n**To Seller Centre, go to Shipping Settings and click the Channel Settings button**\n\n[Interface screenshots showing shipping settings configuration panels]\n\n---\n\n# Filling in the contingency freight value\n\nNext, the screen will ask to enter the shipping cost. Shipping costs can be entered by sales channel value or by city. This setting can vary for each my city/region which will automatically apply for all orders always send normal items except that are established in the contingency chart when they are activated from the place where orders need to go.\n\n## Steps to set per cost state:\n\n**Stage shipping cost per state:**\n\n1. Select a state\n2. Fill in the shipping cost field\n3. Click Save\n\n[Interface screenshots showing state-by-state shipping cost configuration]\n\n**Stage shipping cost per city:**\n\n1. Select a state\n2. Select the 'I set value button for this area'\n3. A new screen will appear. Select the cities you want to inform the shipping cost\n4. Fill in the values next to the respective cities\n5. Click Save\n\n[Interface screenshots showing city-specific shipping cost configuration]\n\n---\n\n# Syncronization Area Settings\n\nThis feature is intended to support seller's serviceable area settings, to identify if the buyer's address is within seller's delivery area and to know if there are any other issues, including when an order is marked as a failed order. Please fill in the Shipping Destination feature (can be found in Shopee Seller Centre on My Shipping > Shipping Settings), and always display an unsupported to buyer. To upload serviceable settings:\n\n1. Login to https://partner.shopeemobile.com/api/v1/top\n2. Navigate to Logistics -> My Shipping > Logistics Settings\n3. Once uploaded, tweak click check the status of serviceable area settings upload via https://partner.shopeemobile.com/api/v1/me\n\n---\n\n# Arrange Shipment\n\nOnce an order is placed by a buyer, it is the Seller APP. Please note the order always will be updated to PROCESSED status after arranging shipment, and can be returned to get_package_detail API, get_order_detail order_status with return status \"READY_TO_SHIP\"\n\nFor detailed steps on API documentation:\n- /api/v2/logistics/get_order_logistics_info\n- /api/v2/logistics/ship_order\n- /api/v2/logistics/get_tracking_info\n\n---\n\n# Order Status and Tracking\n\nOrder status and tracking updates will be performed via the Tracking Update API and will be based on the order number (order SN) which is the same identifier used throughout the above API. Shopee takes end-to-end monitoring of the order and delivery status.\n\n---\n\n# Order Status and Tracking\n\n## Shipment Arrangement\n\nSeller will arrange shipment via ship_order API. Please note that order_status will be updated to PROCESSED status after arranging shipment, and will be returned in get_package_detail API. get_order_detail order_status will still return READY_TO_SHIP.\n\nHere are the links to the API documentation:\n\n- /api/v2/logistics/ship_order\n- /api/v2/order/get_order_detail\n- /api/v2/order/get_package_detail\n\n---\n\n## Order Status and Tracking\n\nOrder status and tracking updates will be performed via the Tracking Update API and will be based on the order number created in Shopee (Order ID, also known as OrderSN). The tracking number will also be required.\n\nTo update the tracking number and order status, use the **v2 logistics update_tracking_status (OpenAPI) endpoint**. The possible statuses are:\n\n1. **Order Sent (logistics_pickup_done)**\n   - The URL and tracking number can be sent when updating the order status to Shipped.\n\n2. **Order Delivered (logistics_delivery_done)**\n   - The Delivered status will only be received if the order already has the Shipped status.\n   - OTP code verification: For Entrega Expressa channel, it is mandatory to have OTP code verification. Shopee will be generating the OTP code after seller arranges shipment. When seller is delivering the parcel to buyer, it is mandatory for seller to retrieve OTP code from buyer, and send it in API request when attempting to update tracking_status to logistics_delivery_done.\n\n3. **Delivery Failure (logistics_delivery_failed)**\n   - The Delivery Failure status will only be received if the order already has the Shipped status.\n   - Failed reason: For Entrega Expressa channel, it is mandatory for seller to send failed_reason when updating tracking_status to logistics_delivery_failed.\n\n**IMPORTANT**: after sending the Order Delivered or Delivery Failed statuses, no further status updates will be allowed, as both are finalizing statuses;\n\n*the tracking_number and tracking_url parameters should only be sent when updating the status to logistics_pickup_done*.\n\nHere is a link to the API documentation **/api/v2/logistics/update_tracking_status**.\n\n---\n\n## Channel Order Flow and Status\n\n### REQUESTED FLOW\n\n```\nUNPAID\n  ↓ 1\nREADY_TO_SHIP\n  ↓ 2\nPROCESSED\n  ↓ 3\nSHIPPED\n  ↓ 4\nTO_CONFIRM_RECEIVE\n  ↓ 5\nCOMPLETED\n```\n\n**Steps:**\n\n1. **(1) Buyer paid the order and seller upload the invoice**\n\n2. **(2) Seller Arrange Shipment (ship_order API)**\n\n3. **(3) Seller updates order status as PICK_UP_DONE via (update_tracking_status API)**\n\n4. **(4) Seller updates order status as DELIVERY_DONE via (update_tracking_status API)**\n\n5. **(5) Buyer confirms receive the package**",
  "metadata": {
    "title": "Quotation API (Entrance Ex.)",
    "summary": "This guide provides information about the Quotation API, which allows sellers to send Shopee-estimated shipping costs and delivery times to buyers. It outlines the requirements for approval and integration, request and response flows, and detailed parameter descriptions for both requests and responses.",
    "keywords": [
      "Quotation API",
      "Shipping Quote",
      "API Integration",
      "Request Parameters",
      "Response Parameters",
      "Shopee",
      "Logistics",
      "Shipping Costs",
      "Delivery Times"
    ],
    "category": "API Reference",
    "tags": [
      "Quotation",
      "Shipping",
      "API",
      "Integration",
      "Logistics"
    ],
    "difficulty": "medium",
    "importance": 4,
    "use_cases": [
      "Calculating shipping costs for buyers at checkout",
      "Integrating seller systems with Shopee's logistics API",
      "Displaying estimated delivery times to buyers",
      "Automating the quotation process for shipping",
      "Verifying buyer's delivery location"
    ],
    "related_apis": [
      "Shipping Quote API",
      "Shipment API",
      "Order (Arrange Pickup API)",
      "Tracking API"
    ]
  }
}