{
  "endpoint": "/v2/product/get_variations",
  "method": "GET",
  "description": "Get the standard/active variation defined by Shopee, which is currently a three-layer tree structure. The top layer is variations, the second layer contains variations_0 and variations_1, and the leaf layer contains variations_2.",
  "parameters": [
    {
      "name": "partner_id",
      "type": "int",
      "required": true,
      "description": "Partner ID is assigned upon registration is successful Required for all APIs"
    },
    {
      "name": "timestamp",
      "type": "timestamp",
      "required": true,
      "description": "This is to indicate the timestamp of the request Required for all requests. Example is 1586168037"
    },
    {
      "name": "access_token",
      "type": "string",
      "required": true,
      "description": "The token for API access. Used to identify your permission to use API. Valid for token.valid_seconds of token."
    },
    {
      "name": "shop_id",
      "type": "int",
      "required": true,
      "description": "Shopee's unique identifier for a shop. Required param for all APIs"
    },
    {
      "name": "sign",
      "type": "string",
      "required": true,
      "description": "Signature generated by partner_id, api_path, timestamp, access_token, and shop_id params. More details at https://partner.test-stable.shopeemobile.com/docs/v2/"
    },
    {
      "name": "category_id",
      "type": "int",
      "required": true,
      "description": "Leaf category id"
    },
    {
      "name": "error",
      "type": "string",
      "description": "Indicate error type if any error. Empty if no error happened"
    },
    {
      "name": "message",
      "type": "string",
      "description": "Indicate error details if any error. Empty if no error happened"
    },
    {
      "name": "warning",
      "type": "string",
      "description": "Warning message"
    },
    {
      "name": "request_id",
      "type": "string",
      "description": "The identifier for API call tracking"
    },
    {
      "name": "standardized_variation_ids",
      "type": "object",
      "children": [
        {
          "name": "variation_id",
          "type": "int",
          "value": "123"
        },
        {
          "name": "variation_name",
          "type": "string",
          "value": "Color"
        }
      ]
    },
    {
      "name": "variation_group_ids",
      "type": "object",
      "children": [
        {
          "name": "variation_group_id",
          "type": "int",
          "value": "1234"
        },
        {
          "name": "variation_group_name",
          "type": "string",
          "value": "group1"
        }
      ]
    }
  ],
  "response_fields": [],
  "update_log": [
    {
      "date": "2024-03-26",
      "change": "New API"
    }
  ],
  "hidden_fields": [],
  "metadata": {
    "total_chunks": 1,
    "chunks_with_errors": 0,
    "total_parameters_before_dedup": 12,
    "total_parameters_after_dedup": 12,
    "update_log_entries": 1,
    "hidden_fields_count": 0,
    "source_results": "workspaces\\v2.product.get_variations\\results\\all_chunks_results.json"
  }
}