{
  "endpoint": "/v2/shop/get_shop_notification",
  "method": "GET",
  "description": "get Order Delete notification. For permission is controlled by App level",
  "parameters": [
    {
      "name": "partner_id",
      "type": "int",
      "required": true,
      "description": "Partner ID is assigned upon registration is successful. Required for all requests"
    },
    {
      "name": "timestamp",
      "type": "timestamp",
      "required": true,
      "description": "This is to indicate the timestamp of the request. Required for all requests. Format in seconds"
    },
    {
      "name": "access_token",
      "type": "string",
      "required": true,
      "description": "The token for API access. Used to identify your permission to the api. Valid for multiple call and expire in 4 hours"
    },
    {
      "name": "shop_id",
      "type": "int",
      "required": true,
      "description": "Shopee's unique identifier for a shop. Required param for shop APIs"
    },
    {
      "name": "sign",
      "type": "string",
      "required": true,
      "description": "Signature generated by partner_id, api path, timestamp, access_token, shop_id and partner_key"
    },
    {
      "name": "cursor",
      "type": "int",
      "required": false,
      "description": "The last notification_id retrieved on the page before using the cursor field(returns last seen notification_id by default). When using cursor as cursor is provided, the latest message from the index will be returned"
    },
    {
      "name": "page_size",
      "type": "int",
      "required": false,
      "description": "Default 10, maximum 50"
    },
    {
      "name": "create_time",
      "type": "int",
      "description": "The notification create time"
    },
    {
      "name": "content",
      "type": "string",
      "description": "The content of the notification"
    },
    {
      "name": "title",
      "type": "string",
      "description": "The content of the notification"
    },
    {
      "name": "url",
      "type": "string",
      "description": "Some notification may be attached with URL, it will redirect to other center"
    }
  ],
  "response_fields": [],
  "update_log": [
    {
      "date": "2024-02-29",
      "change": "New API"
    }
  ],
  "hidden_fields": [],
  "metadata": {
    "total_chunks": 1,
    "chunks_with_errors": 0,
    "total_parameters_before_dedup": 12,
    "total_parameters_after_dedup": 11,
    "update_log_entries": 1,
    "hidden_fields_count": 0,
    "source_results": "workspaces\\v2.shop.get_shop_notification\\results\\all_chunks_results.json"
  }
}